ragasas/__init__.py
ragasas/ragasas.py
ragasas/_core/__init__.py
ragasas/_core/embedder/__init__.py
ragasas/_core/embedder/openai_text_embedder.py
ragasas/_core/embedder/text_embedder.py
ragasas/_core/llm/__init__.py
ragasas/_core/llm/llm.py
ragasas/_core/llm/openai_llm.py
ragasas/_core/vector_store/__init__.py
ragasas/_core/vector_store/faiss_vector_store.py
ragasas/_core/vector_store/vector_store.py
ragasas-1.1.5.dist-info/METADATA
ragasas-1.1.5.dist-info/WHEEL
ragasas-1.1.5.dist-info/top_level.txt
ragasas-1.1.5.dist-info/RECORD
